Workbook

Sheet coffee shop project
A1: Transaction_ID | B1: Transaction_Date | C1: Area Code | D1: State | E1: Market | F1: Market Size | G1: Product Line | H1: Product Type | I1: Product | J1: Type | K1: Inventory | L1: Marketing | M1: Sales | N1: Cogs | O1: Total Expenses | P1: Profit | Q1: Profit Margin | R1: Target Sales | S1: Target COGS | T1: Target Profit | U1: Target Profit Margin | V1: Difference Between Actual and Target Profit
A2: TXN-00001 | B2: 45292 | C2: 715 | D2: Wisconsin | E2: Central | F2: Small Market | G2: Leaves | H2: Tea | I2: Darjeeling | J2: Regular | K2: 454 | L2: 15 | M2: 128 | N2: 49 | O2: 38 | P2: 49 | Q2: 0.3828 | R2: 90 | S2: 40 | T2: 20 | U2: 0.2222 | V2: 29
A3: TXN-00002 | B3: 45292 | C3: 719 | D3: Colorado | E3: Central | F3: Major Market | G3: Beans | H3: Coffee | I3: Amaretto | J3: Regular | K3: 959 | L3: 34 | M3: 302 | N3: 123 | O3: 45 | P3: 134 | Q3: 0.4437 | R3: 290 | S3: 120 | T3: 130 | U3: 0.4483 | V3: 4
A4: TXN-00003 | B4: 45292 | C4: 309 | D4: Illinois | E4: Central | F4: Major Market | G4: Leaves | H4: Herbal Tea | I4: Chamomile | J4: Decaf | K4: 959 | L4: 34 | M4: 302 | N4: 123 | O4: 46 | P4: 133 | Q4: 0.4404 | R4: 280 | S4: 110 | T4: 130 | U4: 0.4643 | V4: 3
A5: TXN-00004 | B5: 45293 | C5: 719 | D5: Colorado | E5: Central | F5: Major Market | G5: Leaves | H5: Tea | I5: Earl Grey | J5: Regular | K5: 1042 | L5: 17 | M5: 133 | N5: 57 | O5: 39 | P5: 43 | Q5: 0.3233 | R5: 100 | S5: 40 | T5: 30 | U5: 0.3 | V5: 13
A6: TXN-00005 | B6: 45293 | C6: 505 | D6: New Mexico | E6: South | F6: Small Market | G6: Leaves | H6: Herbal Tea | I6: Lemon | J6: Decaf | K6: 1000 | L6: 9 | M6: 72 | N6: 31 | O6: 31 | P6: 9 | Q6: 0.125 | R6: 50 | S6: 10 | T6: 30 | U6: 0.6 | V6: -21
A7: TXN-00006 | B7: 45294 | C7: 262 | D7: Wisconsin | E7: Central | F7: Small Market | G7: Leaves | H7: Tea | I7: Earl Grey | J7: Regular | K7: 627 | L7: 49 | M7: 140 | N7: 55 | O7: 79 | P7: -4 | Q7: -0.0286 | R7: 100 | S7: 40 | T7: 0 | U7: 0 | V7: -4
A8: TXN-00007 | B8: 45294 | C8: 985 | D8: Louisiana | E8: South | F8: Small Market | G8: Beans | H8: Coffee | I8: Colombian | J8: Regular | K8: 845 | L8: 13 | M8: 128 | N8: 49 | O8: 25 | P8: 68 | Q8: 0.5313 | R8: 140 | S8: 50 | T8: 70 | U8: 0.5 | V8: -2
A9: TXN-00008 | B9: 45295 | C9: 360 | D9: Washington | E9: West | F9: Small Market | G9: Beans | H9: Espresso | I9: Decaf Espresso | J9: Decaf | K9: 1079 | L9: 24 | M9: 188 | N9: 80 | O9: 45 | P9: 76 | Q9: 0.4043 | R9: 170 | S9: 70 | T9: 60 | U9: 0.3529 | V9: 16
A10: TXN-00009 | B10: 45296 | C10: 715 | D10: Wisconsin | E10: Central | F10: Small Market | G10: Beans | H10: Espresso | I10: Decaf Espresso | J10: Decaf | K10: 573 | L10: 7 | M10: 51 | N10: 22 | O10: 19 | P10: 10 | Q10: 0.1961 | R10: 70 | S10: 20 | T10: 50 | U10: 0.7143 | V10: -40
A11: TXN-00010 | B11: 45296 | C11: 314 | D11: Missouri | E11: Central | F11: Small Market | G11: Leaves | H11: Tea | I11: Green Tea | J11: Regular | K11: 243 | L11: 12 | M11: 74 | N11: 33 | O11: 45 | P11: -4 | Q11: -0.0541 | R11: 60 | S11: 20 | T11: 0 | U11: 0 | V11: -4
A12: TXN-00011 | B12: 45296 | C12: 985 | D12: Louisiana | E12: South | F12: Small Market | G12: Leaves | H12: Herbal Tea | I12: Chamomile | J12: Decaf | K12: 540 | L12: 31 | M12: 228 | N12: 94 | O12: 43 | P12: 114 | Q12: 0.5 | R12: 190 | S12: 80 | T12: 70 | U12: 0.3684 | V12: 44
A13: TXN-00012 | B13: 45298 | C13: 209 | D13: California | E13: West | F13: Major Market | G13: Leaves | H13: Tea | I13: Green Tea | J13: Regular | K13: 659 | L13: 24 | M13: 201 | N13: 75 | O13: 55 | P13: 88 | Q13: 0.4378 | R13: 130 | S13: 50 | T13: 40 | U13: 0.3077 | V13: 48
... A144: TXN-00143 | B144: 45341 | C144: 203 | D144: Connecticut | E144: East | F144: Small Market | G144: Beans | H144: Coffee | I144: Colombian | J144: Regular | K144: 1134 | L144: 42 | M144: 346 | N144: 130 | O144: 73 | P144: 181 | Q144: 0.5231 | R144: 290 | S144: 110 | T144: 130 | U144: 0.4483 | V144: 51
A145: TXN-00144 | B145: 45342 | C145: 262 | D145: Wisconsin | E145: Central | F145: Small Market | G145: Leaves | H145: Herbal Tea | I145: Lemon | J145: Decaf | K145: 851 | L145: 13 | M145: 118 | N145: 48 | O145: 25 | P145: 45 | Q145: 0.3814 | R145: 90 | S145: 30 | T145: 60 | U145: 0.6667
A146: TXN-00145 | B146: 45342 | C146: 361 | D146: Texas | E146: South | F146: Major Market | G146: Beans | H146: Espresso | I146: Caffe Latte | J146: Regular | K146: -1239 | L146: 22 | M146: 179 | N146: 67 | O146: 54 | P146: 70 | Q146: 0.3911 | R146: 120 | S146: 50 | T146: 30 | U146: 0.25 | V146: 40
A147: TXN-00146 | B147: 45342 | C147: 509 | D147: Washington | E147: West | F147: Small Market | G147: Leaves | H147: Herbal Tea | I147: Chamomile | J147: Decaf | K147: 1166 | L147: 37 | M147: 289 | N147: 115 | O147: 69 | P147: 105 | Q147: 0.3633 | R147: 260 | S147: 100 | T147: 110 | U147: 0.4231 | V147: -5
A148: TXN-00147 | B148: 45343 | C148: 702 | D148: Nevada | E148: West | F148: Small Market | G148: Beans | H148: Espresso | I148: Caffe Latte | J148: Regular | K148: 344 | L148: 0 | M148: 43 | N148: 0 | O148: 12 | P148: 31 | Q148: 0.7209 | R148: 40 | S148: 0 | T148: 30 | U148: 0.75 | V148: 1
A149: TXN-00148 | B149: 45343 | C149: 203 | D149: Connecticut | E149: East | F149: Small Market | G149: Leaves | H149: Tea | I149: Green Tea | J149: Regular | K149: 806 | L149: 6 | M149: 64 | N149: 24 | O149: 18 | P149: 27 | Q149: 0.4219 | R149: 60 | S149: 20 | T149: 40 | U149: 0.6667 | V149: -13
A150: TXN-00149 | B150: 45343 | C150: 915 | D150: Texas | E150: South | F150: Major Market | G150: Beans | H150: Espresso | I150: Caffe Mocha | J150: Regular | K150: 930 | L150: 33 | M150: 309 | N150: 118 | O150: 45 | P150: 188 | Q150: 0.6084 | R150: 220 | S150: 90 | T150: 100 | U150: 0.4545 | V150: 88
A151: TXN-00150 | B151: 45343 | C151: 641 | D151: Iowa | E151: Central | F151: Small Market | G151: Leaves | H151: Herbal Tea | I151: Chamomile | J151: Decaf | K151: 1691 | L151: 75 | M151: 567 | N151: 228 | O151: 108 | P151: 291 | Q151: 0.5132 | R151: 490 | S151: 210 | T151: 180 | U151: 0.3673 | V151: 111
A152: TXN-00151 | B152: 45344 | C152: 760 | D152: California | E152: West | F152: Major Market | G152: Leaves | H152: Tea | I152: Earl Grey | J152: Regular | K152: 589 | L152: 14 | M152: 131 | N152: 50 | O152: 26 | P152: 70 | Q152: 0.5344 | R152: 80 | S152: 30 | T152: 40 | U152: 0.5 | V152: 30
A153: TXN-00152 | B153: 45344 | C153: 775 | D153: Nevada | E153: West | F153: Small Market | G153: Beans | H153: Espresso | I153: Caffe Mocha | J153: Regular | K153: 848 | L153: 4 | M153: 42 | N153: 15 | O153: 15 | P153: 13 | Q153: 0.3095 | R153: 30 | S153: 10 | T153: 10 | U153: 0.3333 | V153: 3
A154: TXN-00153 | B154: 45345 | C154: 505 | D154: New Mexico | E154: South | F154: Small Market | G154: Beans | H154: Espresso | I154: Caffe Latte | J154: Regular | K154: -522 | L154: 12 | M154: 81 | N154: 34 | O154: 46 | P154: -6 | Q154: -0.0741 | R154: 50 | S154: 20 | T154: -10 | U154: -0.2 | V154: 4
A155: TXN-00154 | B155: 45345 | C155: 435 | D155: Utah | E155: West | F155: Small Market | G155: Beans | H155: Coffee | I155: Colombian | J155: Regular | K155: 392 | L155: 16 | M155: 121 | N155: 49 | O155: 44 | P155: 31 | Q155: 0.2562 | R155: 130 | S155: 50 | T155: 50 | U155: 0.3846 | V155: -19
A156: TXN-00155 | B156: 45345 | C156: 918 | D156: Oklahoma | E156: South | F156: Small Market | G156: Beans | H156: Espresso | I156: Caffe Latte | J156: Regular | K156: -2248 | L156: 41 | M156: 341 | N156: 134 | O156: 65 | P156: 180 | Q156: 0.5279 | R156: 240 | S156: 100 | T156: 90 | U156: 0.375 | V156: 90
A157: TXN-00156 | B157: 45345 | C157: 978 | D157: Massachusetts | E157: East | F157: Major Market | G157: Beans | H157: Coffee | I157: Colombian | J157: Regular | K157: -3287 | L157: 24 | M157: 454 | N157: 75 | O157: 55 | P157: 324 | Q157: 0.7137 | R157: 400 | S157: 60 | T157: 300 | U157: 0.75 | V157: 24
... A415: TXN-00414 | B415: 45431 | C415: 918 | D415: Oklahoma | E415: South | F415: Small Market | G415: Beans | H415: Espresso | I415: Decaf Espresso | J415: Decaf | K415: 817 | L415: 29 | M415: 236 | N415: 88 | O415: 61 | P415: 107 | Q415: 0.4534 | R415: 170 | S415: 60 | T415: 60 | U415: 0.3529 | V415: 47
A416: TXN-00415 | B416: 45431 | C416: 775 | D416: Nevada | E416: West | F416: Small Market | G416: Leaves | H416: Tea | I416: Green Tea | J416: Regular | K416: 8252 | L416: 111 | M416: 31 | N416: 294 | O416: 145 | P416: -408 | Q416: -13.1613 | R416: 0 | S416: 210 | T416: -320 | U416: #DIV/0! | V416: -88
A417: TXN-00416 | B417: 45432 | C417: 435 | D417: Utah | E417: West | F417: Small Market | G417: Beans | H417: Coffee | I417: Colombian | J417: Regular | K417: 380 | L417: 17 | M417: 124 | N417: 53 | O417: 44 | P417: 27 | Q417: 0.2177 | R417: 140 | S417: 60 | T417: 50 | U417: 0.3571 | V417: -23
A418: TXN-00417 | B418: 45432 | C418: 234 | D418: Ohio | E418: Central | F418: Major Market | G418: Leaves | H418: Tea | I418: Darjeeling | J418: Regular | K418: 788 | L418: 27 | M418: 205 | N418: 82 | O418: 58 | P418: 65 | Q418: 0.3171 | R418: 140 | S418: 50 | T418: 60 | U418: 0.4286 | V418: 5
A419: TXN-00418 | B419: 45433 | C419: 603 | D419: New Hampshire | E419: East | F419: Small Market | G419: Beans | H419: Coffee | I419: Colombian | J419: Regular | K419: 447 | L419: 14 | M419: 121 | N419: 45 | O419: 45 | P419: 36 | Q419: 0.2975 | R419: 90 | S419: 30 | T419: 50 | U419: 0.5556 | V419: -14
A420: TXN-00419 | B420: 45433 | C420: 323 | D420: California | E420: West | F420: Major Market | G420: Leaves | H420: Herbal Tea | I420: Mint | J420: Decaf | K420: 536 | L420: 13 | M420: 98 | N420: 40 | O420: 25 | P420: 40 | Q420: 0.4082 | R420: 80 | S420: 30 | T420: 30 | U420: 0.375 | V420: 10
A421: TXN-00420 | B421: 45433 | C421: 225 | D421: Louisiana | E421: South | F421: Small Market | G421: Beans | H421: Coffee | I421: Decaf Irish Cream | J421: Decaf | K421: 851 | L421: 13 | M421: 118 | N421: 48 | O421: 25 | P421: 45 | Q421: 0.3814 | R421: 160 | S421: 70 | T421: 80 | U421: 0.5 | V421: -35
A422: TXN-00421 | B422: 45434 | C422: 318 | D422: Louisiana | E422: South | F422: Small Market | G422: Beans | H422: Espresso | I422: Caffe Mocha | J422: Regular | K422: 321 | L422: 16 | M422: 150 | N422: 53 | O422: 39 | P422: 73 | Q422: 0.4867 | R422: 100 | S422: 40 | T422: 30 | U422: 0.3 | V422: 43
A423: TXN-00422 | B423: 45434 | C423: 360 | D423: Washington | E423: West | F423: Small Market | G423: Leaves | H423: Tea | I423: Earl Grey | J423: Regular | K423: 449 | L423: 14 | M423: 113 | N423: 46 | O423: 36 | P423: 31 | Q423: 0.2743 | R423: 50 | S423: 20 | T423: 30 | U423: 0.6 | V423: 1
A424: TXN-00423 | B424: 45434 | C424: 503 | D424: Oregon | E424: West | F424: Small Market | G424: Leaves | H424: Herbal Tea | I424: Chamomile | J424: Decaf | K424: 823 | L424: 7 | M424: 63 | N424: 25 | O424: 19 | P424: 19 | Q424: 0.3016 | R424: 50 | S424: 20 | T424: 20 | U424: 0.4 | V424: -1
A425: TXN-00424 | B425: 45434 | C425: 650 | D425: California | E425: West | F425: Major Market | G425: Leaves | H425: Tea | I425: Green Tea | J425: Regular | K425: 659 | L425: 24 | M425: 189 | N425: 75 | O425: 55 | P425: 59 | Q425: 0.3122 | R425: 130 | S425: 50 | T425: 40 | U425: 0.3077 | V425: 19
A426: TXN-00425 | B426: 45435 | C426: 435 | D426: Utah | E426: West | F426: Small Market | G426: Leaves | H426: Herbal Tea | I426: Chamomile | J426: Decaf | K426: 316 | L426: 14 | M426: 120 | N426: 46 | O426: 37 | P426: 45 | Q426: 0.375 | R426: 100 | S426: 40 | T426: 30 | U426: 0.3 | V426: 15
A427: TXN-00426 | B427: 45435 | C427: 641 | D427: Iowa | E427: Central | F427: Small Market | G427: Beans | H427: Coffee | I427: Amaretto | J427: Regular | K427: 851 | L427: 4 | M427: 41 | N427: 16 | O427: 15 | P427: 10 | Q427: 0.2439 | R427: 40 | S427: 10 | T427: 20 | U427: 0.5 | V427: -10
A428: TXN-00427 | B428: 45436 | C428: 325 | D428: Texas | E428: South | F428: Major Market | G428: Leaves | H428: Herbal Tea | I428: Chamomile | J428: Decaf | K428: 405 | L428: 17 | M428: 131 | N428: 52 | O428: 45 | P428: 39 | Q428: 0.2977 | R428: 110 | S428: 30 | T428: 70 | U428: 0.6364 | V428: -31
... A622: TXN-00621 | B622: 45508 | C622: 618 | D622: Illinois | E622: Central | F622: Major Market | G622: Leaves | H622: Herbal Tea | I622: Chamomile | J622: Decaf | K622: 959 | L622: 34 | M622: 322 | N622: 123 | O622: 46 | P622: 197 | Q622: 0.6118 | R622: 280 | S622: 110 | T622: 130 | U622: 0.4643 | V622: 67
A623: TXN-00622 | B623: 45508 | C623: 702 | D623: Nevada | E623: West | F623: Small Market | G623: Leaves | H623: Tea | I623: Green Tea | J623: Regular | K623: 7653 | L623: 93 | M623: 32 | N623: 245 | O623: 127 | P623: -340 | Q623: -10.625 | R623: 0 | S623: 180 | T623: -280 | U623: #DIV/0! | V623: -60
A624: TXN-00623 | B624: 45509 | C624: 636 | D624: Missouri | E624: Central | F624: Small Market | G624: Beans | H624: Espresso | I624: Decaf Espresso | J624: Decaf | K624: 836 | L624: 9 | M624: 86 | N624: 33 | O624: 21 | P624: 40 | Q624: 0.4651 | R624: 100 | S624: 40 | T624: 50 | U624: 0.5 | V624: -10
A625: TXN-00624 | B625: 45509 | C625: 503 | D625: Oregon | E625: West | F625: Small Market | G625: Beans | H625: Espresso | I625: Caffe Mocha | J625: Regular | K625: 424 | L625: 17 | M625: 127 | N625: 54 | O625: 45 | P625: 28 | Q625: 0.2205 | R625: 120 | S625: 50 | T625: 40 | U625: 0.3333 | V625: -12
A626: TXN-00625 | B626: 45509 | C626: 720 | D626: Colorado | E626: Central | F626: Major Market | G626: Beans | H626: Coffee | I626: Decaf Irish Cream | J626: Decaf | K626: 1003 | L626: 24 | M626: 210 | N626: 86 | O626: 36 | P626: 88 | Q626: 0.419 | R626: 200 | S626: 80 | T626: 90 | U626: 0.45 | V626: -2
A627: TXN-00626 | B627: 45511 | C627: 918 | D627: Oklahoma | E627: South | F627: Small Market | G627: Beans | H627: Espresso | I627: Caffe Mocha | J627: Regular | K627: 482 | L627: 8 | M627: 80 | N627: 32 | O627: 19 | P627: 29 | Q627: 0.3625 | R627: 60 | S627: 20 | T627: 30 | U627: 0.5 | V627: -1
A628: TXN-00627 | B628: 45511 | C628: 860 | D628: Connecticut | E628: East | F628: Small Market | G628: Leaves | H628: Tea | I628: Darjeeling | J628: Regular | K628: 885 | L628: 15 | M628: 141 | N628: 54 | O628: 27 | P628: 76 | Q628: 0.539 | R628: 130 | S628: 50 | T628: 60 | U628: 0.4615 | V628: 16
A629: TXN-00628 | B629: 45512 | C629: 203 | D629: Connecticut | E629: East | F629: Small Market | G629: Beans | H629: Espresso | I629: Decaf Espresso | J629: Decaf | K629: 375 | L629: 15 | M629: 118 | N629: 47 | O629: 43 | P629: 31 | Q629: 0.2627 | R629: 90 | S629: 30 | T629: 50 | U629: 0.5556 | V629: -19
A630: TXN-00629 | B630: 45512 | C630: 603 | D630: New Hampshire | E630: East | F630: Small Market | G630: Beans | H630: Espresso | I630: Caffe Mocha | J630: Regular | K630: 320 | L630: 41 | M630: 116 | N630: 45 | O630: 71 | P630: -10 | Q630: -0.0862 | R630: 90 | S630: 30 | T630: 30 | U630: 0.3333 | V630: -40
A631: TXN-00630 | B631: 45512 | C631: 315 | D631: New York | E631: East | F631: Major Market | G631: Beans | H631: Coffee | I631: Colombian | J631: Regular | K631: 2642 | L631: 97 | M631: 745 | N631: 279 | O631: 149 | P631: 402 | Q631: 0.5396 | R631: 620 | S631: 250 | T631: 250 | U631: 0.4032 | V631: 152
A632: TXN-00631 | B632: 45512 | C632: 702 | D632: Nevada | E632: West | F632: Small Market | G632: Leaves | H632: Tea | I632: Green Tea | J632: Regular | K632: 7058 | L632: 96 | M632: 22 | N632: 255 | O632: 129 | P632: -539 | Q632: -24.5 | R632: 0 | S632: 110 | T632: -170 | U632: #DIV/0! | V632: -369
A633: TXN-00632 | B633: 45513 | C633: 234 | D633: Ohio | E633: Central | F633: Major Market | G633: Beans | H633: Coffee | I633: Amaretto | J633: Regular | K633: 411 | L633: 19 | M633: 147 | N633: 59 | O633: 46 | P633: 49 | Q633: 0.3333 | R633: 130 | S633: 50 | T633: 50 | U633: 0.3846 | V633: -1
A634: TXN-00633 | B634: 45513 | C634: 405 | D634: Oklahoma | E634: South | F634: Small Market | G634: Beans | H634: Espresso | I634: Decaf Espresso | J634: Decaf | K634: 817 | L634: 29 | M634: 221 | N634: 88 | O634: 61 | P634: 72 | Q634: 0.3258 | R634: 170 | S634: 60 | T634: 60 | U634: 0.3529 | V634: 12
A635: TXN-00634 | B635: 45514 | C635: 435 | D635: Utah | E635: West | F635: Small Market | G635: Beans | H635: Espresso | I635: Decaf Espresso | J635: Decaf | K635: 881 | L635: 11 | M635: 99 | N635: 40 | O635: 22 | P635: 37 | Q635: 0.3737 | R635: 80 | S635: 20 | T635: 60 | U635: 0.75 | V635: -23
A636: TXN-00635 | B636: 45514 | C636: 630 | D636: Illinois | E636: Central | F636: Major Market | G636: Beans | H636: Espresso | I636: Decaf Espresso | J636: Decaf | K636: 1820 | L636: 70 | M636: 501 | N636: 250 | O636: 94 | P636: 157 | Q636: 0.3134 | R636: 640 | S636: 320 | T636: 240 | U636: 0.375 | V636: -83
A637: TXN-00636 | B637: 45515 | C637: 775 | D637: Nevada | E637: West | F637: Small Market | G637: Beans | H637: Coffee | I637: Colombian | J637: Regular | K637: 243 | L637: 12 | M637: 79 | N637: 33 | O637: 45 | P637: -6 | Q637: -0.0759 | R637: 80 | S637: 30 | T637: 10 | U637: 0.125 | V637: -16
A638: TXN-00637 | B638: 45515 | C638: 505 | D638: New Mexico | E638: South | F638: Small Market | G638: Beans | H638: Coffee | I638: Colombian | J638: Regular | K638: 447 | L638: 14 | M638: 121 | N638: 45 | O638: 46 | P638: 34 | Q638: 0.281 | R638: 160 | S638: 50 | T638: 80 | U638: 0.5 | V638: -46
A639: TXN-00638 | B639: 45515 | C639: 818 | D639: California | E639: West | F639: Major Market | G639: Beans | H639: Espresso | I639: Caffe Mocha | J639: Regular | K639: 912 | L639: 109 | M639: 289 | N639: 121 | O639: 142 | P639: 26 | Q639: 0.09 | R639: 280 | S639: 110 | T639: 40 | U639: 0.1429 | V639: -14
A640: TXN-00639 | B640: 45516 | C640: 509 | D640: Washington | E640: West | F640: Small Market | G640: Leaves | H640: Herbal Tea | I640: Lemon | J640: Decaf | K640: 829 | L640: 13 | M640: 127 | N640: 48 | O640: 24 | P640: 70 | Q640: 0.5512 | R640: 90 | S640: 30 | T640: 60 | U640: 0.6667 | V640: 10
A641: TXN-00640 | B641: 45516 | C641: 206 | D641: Washington | E641: West | F641: Small Market | G641: Leaves | H641: Tea | I641: Earl Grey | J641: Regular | K641: 454 | L641: 15 | M641: 120 | N641: 49 | O641: 37 | P641: 34 | Q641: 0.2833 | R641: 80 | S641: 30 | T641: 30 | U641: 0.375 | V641: 4
A642: TXN-00641 | B642: 45516 | C642: 754 | D642: Florida | E642: East | F642: Major Market | G642: Beans | H642: Coffee | I642: Colombian | J642: Regular | K642: 798 | L642: 25 | M642: 197 | N642: 78 | O642: 56 | P642: 63 | Q642: 0.3198 | R642: 170 | S642: 70 | T642: 60 | U642: 0.3529 | V642: 3
A643: TXN-00642 | B643: 45516 | C643: 904 | D643: Florida | E643: East | F643: Major Market | G643: Leaves | H643: Herbal Tea | I643: Chamomile | J643: Decaf | K643: 573 | L643: 7 | M643: 54 | N643: 22 | O643: 19 | P643: 15 | Q643: 0.2778 | R643: 20 | S643: 0 | T643: 20 | U643: 1 | V643: -5
A644: TXN-00643 | B644: 45516 | C644: 775 | D644: Nevada | E644: West | F644: Small Market | G644: Leaves | H644: Herbal Tea | I644: Mint | J644: Decaf | K644: 803 | L644: 36 | M644: 296 | N644: 113 | O644: 58 | P644: 159 | Q644: 0.5372 | R644: 250 | S644: 100 | T644: 100 | U644: 0.4 | V644: 59
... A920: TXN-00919 | B920: 45610 | C920: 626 | D920: California | E920: West | F920: Major Market | G920: Leaves | H920: Herbal Tea | I920: Chamomile | J920: Decaf | K920: 1003 | L920: 24 | M920: 210 | N920: 86 | O920: 35 | P920: 89 | Q920: 0.4238 | R920: 190 | S920: 80 | T920: 80 | U920: 0.4211 | V920: 9
A921: TXN-00920 | B921: 45610 | C921: 775 | D921: Nevada | E921: West | F921: Small Market | G921: Leaves | H921: Tea | I921: Green Tea | J921: Regular | K921: 7653 | L921: 93 | M921: 34 | N921: 245 | O921: 127 | P921: -505 | Q921: -14.8529 | R921: 0 | S921: 180 | T921: -280 | U921: #DIV/0! | V921: -225
A922: TXN-00921 | B922: 45611 | C922: 515 | D922: Iowa | E922: Central | F922: Small Market | G922: Leaves | H922: Tea | I922: Earl Grey | J922: Regular | K922: 1756 | L922: 96 | M922: 604 | N922: 255 | O922: 129 | P922: 272 | Q922: 0.4503 | R922: 400 | S922: 170 | T922: 130 | U922: 0.325 | V922: 142
A923: TXN-00922 | B923: 45612 | C923: 603 | D923: New Hampshire | E923: East | F923: Small Market | G923: Leaves | H923: Tea | I923: Green Tea | J923: Regular | K923: 430 | L923: 0 | M923: 43 | N923: 0 | O923: 11 | P923: 32 | Q923: 0.7442 | R923: 40 | S923: 0 | T923: 40 | U923: 1 | V923: -8
A924: TXN-00923 | B924: 45612 | C924: 603 | D924: New Hampshire | E924: East | F924: Small Market | G924: Leaves | H924: Tea | I924: Green Tea | J924: Regular | K924: 344 | L924: 0 | M924: 46 | N924: 0 | O924: 11 | P924: 47 | Q924: 1.0217 | R924: 40 | S924: 0 | T924: 30 | U924: 0.75 | V924: 17
A925: TXN-00924 | B925: 45612 | C925: 516 | D925: New York | E925: East | F925: Major Market | G925: Leaves | H925: Tea | I925: Darjeeling | J925: Regular | K925: 971 | L925: 30 | M925: 265 | N925: 108 | O925: 42 | P925: 115 | Q925: 0.434 | R925: 280 | S925: 110 | T925: 140 | U925: 0.5 | V925: -25
A926: TXN-00925 | B926: 45612 | C926: 573 | D926: Missouri | E926: Central | F926: Small Market | G926: Leaves | H926: Herbal Tea | I926: Lemon | J926: Decaf | K926: 1698 | L926: 26 | M926: 109 | N926: 86 | O926: 49 | P926: -26 | Q926: -0.2385 | R926: 80 | S926: 60 | T926: 10 | U926: 0.125 | V926: -36
A927: TXN-00926 | B927: 45612 | C927: 224 | D927: Illinois | E927: Central | F927: Major Market | G927: Beans | H927: Espresso | I927: Caffe Mocha | J927: Regular | K927: 1691 | L927: 75 | M927: 532 | N927: 228 | O927: 108 | P927: 196 | Q927: 0.3684 | R927: 680 | S927: 290 | T927: 290 | U927: 0.4265 | V927: -94
A928: TXN-00927 | B928: 45613 | C928: 512 | D928: Texas | E928: South | F928: Major Market | G928: Beans | H928: Espresso | I928: Caffe Latte | J928: Regular | K928: -1239 | L928: 22 | M928: 168 | N928: 67 | O928: 54 | P928: 47 | Q928: 0.2798 | R928: 120 | S928: 50 | T928: 30 | U928: 0.25 | V928: 17
A929: TXN-00928 | B929: 45613 | C929: 985 | D929: Louisiana | E929: South | F929: Small Market | G929: Leaves | H929: Herbal Tea | I929: Lemon | J929: Decaf | K929: 619 | L929: 25 | M929: 153 | N929: 68 | O929: 59 | P929: 26 | Q929: 0.1699 | R929: 140 | S929: 60 | T929: 30 | U929: 0.2143 | V929: -4
A930: TXN-00929 | B930: 45613 | C930: 702 | D930: Nevada | E930: West | F930: Small Market | G930: Leaves | H930: Herbal Tea | I930: Chamomile | J930: Decaf | K930: 898 | L930: 113 | M930: 318 | N930: 125 | O930: 147 | P930: 39 | Q930: 0.1226 | R930: 240 | S930: 90 | T930: 60 | U930: 0.25 | V930: -21
A931: TXN-00930 | B931: 45615 | C931: 262 | D931: Wisconsin | E931: Central | F931: Small Market | G931: Beans | H931: Espresso | I931: Decaf Espresso | J931: Decaf | K931: 567 | L931: 7 | M931: 56 | N931: 24 | O931: 19 | P931: 13 | Q931: 0.2321 | R931: 70 | S931: 30 | T931: 30 | U931: 0.4286 | V931: -17
A932: TXN-00931 | B932: 45615 | C932: 959 | D932: Connecticut | E932: East | F932: Small Market | G932: Beans | H932: Espresso | I932: Decaf Espresso | J932: Decaf | K932: 392 | L932: 16 | M932: 114 | N932: 49 | O932: 44 | P932: 21 | Q932: 0.1842 | R932: 110 | S932: 40 | T932: 40 | U932: 0.3636 | V932: -19
A933: TXN-00932 | B933: 45615 | C933: 561 | D933: Florida | E933: East | F933: Major Market | G933: Beans | H933: Espresso | I933: Decaf Espresso | J933: Decaf | K933: 557 | L933: 25 | M933: 180 | N933: 77 | O933: 52 | P933: 51 | Q933: 0.2833 | R933: 170 | S933: 70 | T933: 60 | U933: 0.3529 | V933: -9
... A958: TXN-00957 | B958: 45623 | C958: 702 | D958: Nevada | E958: West | F958: Small Market | G958: Leaves | H958: Tea | I958: Earl Grey | J958: Regular | K958: 1820 | L958: 70 | M958: 501 | N958: 250 | O958: 94 | P958: 157 | Q958: 0.3134 | R958: 360 | S958: 180 | T958: 100 | U958: 0.2778 | V958: 57
A959: TXN-00958 | B959: 45623 | C959: 775 | D959: Nevada | E959: West | F959: Small Market | G959: Leaves | H959: Tea | I959: Green Tea | J959: Regular | K959: 8252 | L959: 111 | M959: 33 | N959: 294 | O959: 145 | P959: -605 | Q959: -18.3333 | R959: 0 | S959: 210 | T959: -320 | U959: #DIV/0! | V959: -285
A960: TXN-00959 | B960: 45624 | C960: 573 | D960: Missouri | E960: Central | F960: Small Market | G960: Leaves | H960: Tea | I960: Earl Grey | J960: Regular | K960: 211 | L960: 12 | M960: 81 | N960: 34 | O960: 45 | P960: -4 | Q960: -0.0494 | R960: 60 | S960: 20 | T960: 0 | U960: 0 | V960: -4
A961: TXN-00960 | B961: 45627 | C961: 801 | D961: Utah | E961: West | F961: Small Market | G961: Leaves | H961: Herbal Tea | I961: Chamomile | J961: Decaf | K961: 316 | L961: 14 | M961: 113 | N961: 46 | O961: 37 | P961: 30 | Q961: 0.2655 | R961: 100 | S961: 40 | T961: 30 | U961: 0.3 | V961: 0
A962: TXN-00961 | B962: 45628 | C962: 435 | D962: Utah | E962: West | F962: Small Market | G962: Beans | H962: Espresso | I962: Caffe Latte | J962: Regular | K962: 836 | L962: 9 | M962: 81 | N962: 33 | O962: 21 | P962: 27 | Q962: 0.3333 | R962: 70 | S962: 30 | T962: 30 | U962: 0.4286 | V962: -3
A963: TXN-00962 | B963: 45628 | C963: 475 | D963: Connecticut | E963: East | F963: Small Market | G963: Beans | H963: Espresso | I963: Caffe Mocha | J963: Regular | K963: 613 | L963: 55 | M963: 157 | N963: 61 | O963: 84 | P963: 3 | Q963: 0.0191 | R963: 140 | S963: 60 | T963: 10 | U963: 0.0714 | V963: -7
A964: TXN-00963 | B964: 45628 | C964: 775 | D964: Nevada | E964: West | F964: Small Market | G964: Leaves | H964: Tea | I964: Earl Grey | J964: Regular | K964: 1755 | L964: 66 | M964: 509 | N964: 239 | O964: 90 | P964: 221 | Q964: 0.4342 | R964: 230 | S964: 110 | T964: 80 | U964: 0.3478 | V964: 141
A965: TXN-00964 | B965: 45629 | C965: 936 | D965: Texas | E965: South | F965: Major Market | G965: Leaves | H965: Herbal Tea | I965: Chamomile | J965: Decaf | K965: 411 | L965: 19 | M965: 147 | N965: 59 | O965: 47 | P965: 47 | Q965: 0.3197 | R965: 120 | S965: 50 | T965: 40 | U965: 0.3333 | V965: 7
A966: TXN-00965 | B966: 45629 | C966: 347 | D966: New York | E966: East | F966: Major Market | G966: Beans | H966: Coffee | I966: Colombian | J966: Regular | K966: 2580 | L966: 87 | M966: 623 | N966: 249 | O966: 138 | P966: 236 | Q966: 0.3788 | R966: 560 | S966: 220 | T966: 230 | U966: 0.4107 | V966: 6
A967: TXN-00966 | B967: 45629 | C967: 719 | D967: Colorado | E967: Central | F967: Major Market | G967: Beans | H967: Coffee | I967: Amaretto | J967: Regular | K967: 915 | L967: 34 | M967: 322 | N967: 123 | O967: 46 | P967: 197 | Q967: 0.6118 | R967: 300 | S967: 120 | T967: 160 | U967: 0.5333 | V967: 37
A968: TXN-00967 | B968: 45629 | C968: 916 | D968: California | E968: West | F968: Major Market | G968: Leaves | H968: Herbal Tea | I968: Chamomile | J968: Decaf | K968: 1003 | L968: 24 | M968: 224 | N968: 86 | O968: 35 | P968: 132 | Q968: 0.5893 | R968: 190 | S968: 80 | T968: 80 | U968: 0.4211 | V968: 52
A969: TXN-00968 | B969: 45630 | C969: 775 | D969: Nevada | E969: West | F969: Small Market | G969: Beans | H969: Espresso | I969: Caffe Mocha | J969: Regular | K969: 851 | L969: 4 | M969: 41 | N969: 16 | O969: 15 | P969: 10 | Q969: 0.2439 | R969: 30 | S969: 10 | T969: 10 | U969: 0.3333 | V969: 0
A970: TXN-00969 | B970: 45631 | C970: 603 | D970: New Hampshire | E970: East | F970: Small Market | G970: Leaves | H970: Herbal Tea | I970: Lemon | J970: Decaf | K970: 240 | L970: 12 | M970: 77 | N970: 34 | O970: 46 | P970: -3 | Q970: -0.039 | R970: 40 | S970: 10 | T970: 20 | U970: 0.5 | V970: -23
A971: TXN-00970 | B971: 45631 | C971: 972 | D971: Texas | E971: South | F971: Major Market | G971: Beans | H971: Espresso | I971: Caffe Mocha | J971: Regular | K971: 959 | L971: 34 | M971: 302 | N971: 123 | O971: 46 | P971: 133 | Q971: 0.4404 | R971: 230 | S971: 90 | T971: 110 | U971: 0.4783 | V971: 23
... A979: TXN-00978 | B979: 45632 | C979: 775 | D979: Nevada | E979: West | F979: Small Market | G979: Leaves | H979: Tea | I979: Earl Grey | J979: Regular | K979: 1755 | L979: 66 | M979: 478 | N979: 239 | O979: 90 | P979: 149 | Q979: 0.3117 | R979: 230 | S979: 110 | T979: 80 | U979: 0.3478 | V979: 69
A980: TXN-00979 | B980: 45632 | C980: 702 | D980: Nevada | E980: West | F980: Small Market | G980: Leaves | H980: Tea | I980: Green Tea | J980: Regular | K980: 7058 | L980: 96 | M980: 21 | N980: 255 | O980: 129 | P980: -363 | Q980: -17.2857 | R980: 0 | S980: 110 | T980: -170 | U980: #DIV/0! | V980: -193
A981: TXN-00980 | B981: 45633 | C981: 318 | D981: Louisiana | E981: South | F981: Small Market | G981: Beans | H981: Espresso | I981: Decaf Espresso | J981: Decaf | K981: 449 | L981: 14 | M981: 113 | N981: 46 | O981: 37 | P981: 30 | Q981: 0.2655 | R981: 60 | S981: 20 | T981: 40 | U981: 0.6667 | V981: -10
A982: TXN-00981 | B982: 45633 | C982: 541 | D982: Oregon | E982: West | F982: Small Market | G982: Beans | H982: Coffee | I982: Decaf Irish Cream | J982: Decaf | K982: 435 | L982: 13 | M982: 108 | N982: 41 | O982: 35 | P982: 37 | Q982: 0.3426 | R982: 120 | S982: 40 | T982: 50 | U982: 0.4167 | V982: -13
A983: TXN-00982 | B983: 45634 | C983: 641 | D983: Iowa | E983: Central | F983: Small Market | G983: Beans | H983: Espresso | I983: Caffe Mocha | J983: Regular | K983: 800 | L983: 6 | M983: 62 | N983: 23 | O983: 17 | P983: 27 | Q983: 0.4355 | R983: 70 | S983: 20 | T983: 50 | U983: 0.7143 | V983: -23
A984: TXN-00983 | B984: 45634 | C984: 716 | D984: New York | E984: East | F984: Major Market | G984: Leaves | H984: Tea | I984: Darjeeling | J984: Regular | K984: 1003 | L984: 24 | M984: 210 | N984: 86 | O984: 35 | P984: 89 | Q984: 0.4238 | R984: 210 | S984: 90 | T984: 90 | U984: 0.4286 | V984: -1
A985: TXN-00984 | B985: 45634 | C985: 920 | D985: Wisconsin | E985: Central | F985: Small Market | G985: Beans | H985: Espresso | I985: Caffe Mocha | J985: Regular | K985: 1063 | L985: 23 | M985: 164 | N985: 75 | O985: 44 | P985: 45 | Q985: 0.2744 | R985: 200 | S985: 90 | T985: 70 | U985: 0.35 | V985: -25
A986: TXN-00985 | B986: 45635 | C986: 959 | D986: Connecticut | E986: East | F986: Small Market | G986: Leaves | H986: Tea | I986: Green Tea | J986: Regular | K986: 806 | L986: 6 | M986: 60 | N986: 24 | O986: 18 | P986: 18 | Q986: 0.3 | R986: 60 | S986: 20 | T986: 40 | U986: 0.6667 | V986: -22
...

Sheet coffe shop project(excel)
B1: Coffee Shop Performance
B2: FY 2024
B4: Total Revenue | D4: Total Profit | F4: Profit Margin
B5: =SUM('coffee shop project'!M:M) -> 202895 | D5: =SUM('coffee shop project'!P:P) -> 64311 | F5: =SUM('coffee shop project'!P:P)/SUM('coffee shop project'!M:M) -> 0.3169669
B8: Sale Achievment | D8: Profit Achievment | F8: Transaction
B9: =SUM('coffee shop project'!M:M)/SUM('coffee shop project'!R:R) -> 1.1338717 | D9: =SUM('coffee shop project'!P:P)/SUM('coffee shop project'!T:T) -> 1.0064319 | F9: =ROWS('coffee shop project'!A2:A1063) -> 1062
B12: Budget VS Actual variance
B13: Metric | C13: Budget | D13: Actuall | E13: Variance $ | F13: Variance % | G13: Status
B14: Revenue | C14: =SUM('coffee shop project'!R:R) -> 178940 | D14: =SUM('coffee shop project'!M:M) -> 202895 | E14: =D14-C14 -> 23955 | F14: =E14/C14 -> 0.13387169 | G14: Above
B15: Profit | C15: =SUM('coffee shop project'!T:T) -> 63900 | D15: =SUM('coffee shop project'!P:P) -> 64311 | E15: =D15-C15 -> 411 | F15: =E15/D15 -> 0.0063908196 | G15: On Target
B16: Cogs | C16: =SUM('coffee shop project'!S:S) -> 76120 | D16: =SUM('coffee shop project'!N:N) -> 87508 | E16: =D16-C16 -> 11388 | F16: =E16/D16 -> 0.13013667 | G16: Above
B19: Quartrly Summary(2024) | H19: Quartrly Forcast (2025)
C20: 1 | D20: 2 | E20: 3 | F20: 4 | H20: 5 | I20: 6 | J20: 7 | K20: 8
B21: Revenue | C21: =SUMIFS('coffee shop project'!M:M,'coffee shop project'!B:B, ">=1/1/2024",'coffee shop project'!B:B, "<=03/31/2024") -> 49221 | D21: =SUMIFS('coffee shop project'!M:M,'coffee shop project'!B:B, ">=4/1/2024",'coffee shop project'!B:B, "<=06/30/2024") -> 54512 | E21: =SUMIFS('coffee shop project'!M:M,'coffee shop project'!B:B, ">=7/1/2024",'coffee shop project'!B:B, "<=09/30/2024") -> 47823 | F21: =SUMIFS('coffee shop project'!M:M,'coffee shop project'!B:B,">=10/1/2024",'coffee shop project'!B:B,"<=12/31/2024") -> 51339 | H21: =_xlfn.FORECAST.LINEAR(H20,C21:F21,C20:F20) -> 50640 | I21: =_xlfn.FORECAST.LINEAR(I20,C21:F21,C20:F20) -> 50606.5 | J21: =_xlfn.FORECAST.LINEAR(J20,C21:F21,C20:F20) -> 50573 | K21: =_xlfn.FORECAST.LINEAR(K20,C21:F21,C20:F20) -> 50539.5
B22: Profit | C22: =SUMIFS('coffee shop project'!P:P,'coffee shop project'!B:B, ">=1/1/2024",'coffee shop project'!B:B, "<=03/31/2024") -> 16298 | D22: =SUMIFS('coffee shop project'!P:P,'coffee shop project'!B:B, ">=4/1/2024",'coffee shop project'!B:B, "<=06/30/2024") -> 17103 | E22: =SUMIFS('coffee shop project'!P:P,'coffee shop project'!B:B, ">=7/1/2024",'coffee shop project'!B:B, "<=09/30/2024") -> 14894 | F22: =SUMIFS('coffee shop project'!P:P,'coffee shop project'!B:B,">=10/1/2024",'coffee shop project'!B:B,"<=12/31/2024") -> 16016 | H22: =_xlfn.FORECAST.LINEAR(H20,C22:F22,C20:F20) -> 15314 | I22: =_xlfn.FORECAST.LINEAR(I20,C22:F22,C20:F20) -> 15008.5 | J22: =_xlfn.FORECAST.LINEAR(J20,C22:F22,C20:F20) -> 14703 | K22: =_xlfn.FORECAST.LINEAR(K20,C22:F22,C20:F20) -> 14397.5
B23: Cogs | C23: =SUMIFS('coffee shop project'!N:N,'coffee shop project'!B:B, ">=1/1/2024",'coffee shop project'!B:B, "<=03/31/2024") -> 20911 | D23: =SUMIFS('coffee shop project'!N:N,'coffee shop project'!B:B, ">=4/1/2024",'coffee shop project'!B:B, "<=06/30/2024") -> 23618 | E23: =SUMIFS('coffee shop project'!N:N,'coffee shop project'!B:B, ">=7/1/2024",'coffee shop project'!B:B, "<=09/30/2024") -> 20589 | F23: =SUMIFS('coffee shop project'!N:N,'coffee shop project'!B:B,">=10/1/2024",'coffee shop project'!B:B,"<=12/31/2024") -> 22390 | H23: =_xlfn.FORECAST.LINEAR(H20,C23:F23,C20:F20) -> 22229 | I23: =_xlfn.FORECAST.LINEAR(I20,C23:F23,C20:F20) -> 22369.8 | J23: =_xlfn.FORECAST.LINEAR(J20,C23:F23,C20:F20) -> 22510.6 | K23: =_xlfn.FORECAST.LINEAR(K20,C23:F23,C20:F20) -> 22651.4
B26: TOP 5 Products
C27: Column Labels
C28: Colombian | D28: Lemon | E28: Caffe Mocha | F28: Chamomile | G28: Decaf Espresso | H28: Grand Total
B29: Sum of Sales | C29: 30761 | D29: 24048 | E29: 21716 | F29: 19295 | G29: 18888 | H29: 114708
B32: TOP 5 STATES
C33: Column Labels
C34: California | D34: New York | E34: Illinois | F34: Nevada | G34: Iowa | H34: Grand Total
B35: Sum of Sales | C35: 23032 | D35: 17731 | E35: 16812 | F35: 14822 | G35: 13359 | H35: 85756
B38: Key Insights
B40: Revenue Trends | D40: Revenue Exceeded target by 13.39%
B41: Quartrly Performance | D41: Revenue peaks on Q2
B42: Product Performance | D42: Colombian Coffee genereted the highest revenue
